WebTool/WordpressExploit.py
WebTool/__init__.py
WebTool/cms.py
WebTool/domainGrabbere.py
WebTool/proxyGrabber.py
WebTool/reverIpe.py
WebTool/spider.py
WebTool/test.py
Systemadminbd_WebTool-1.1.dist-info/LICENSE
Systemadminbd_WebTool-1.1.dist-info/METADATA
Systemadminbd_WebTool-1.1.dist-info/WHEEL
Systemadminbd_WebTool-1.1.dist-info/entry_points.txt
Systemadminbd_WebTool-1.1.dist-info/top_level.txt
Systemadminbd_WebTool-1.1.dist-info/RECORD
